[
  {
    "id": "27c9d2ab-ad27-42f5-b00a-fb66c126f522",
    "createdAt": "2026-03-27T19:45:42.979Z",
    "type": "analyze_jewelry",
    "status": "ok",
    "userId": "c0d04b59-e946-4b9f-8d40-2ab44a912ff8",
    "platform": "instagram",
    "durationMs": 14416,
    "estimatedCostUsd": 0.03,
    "message": "analyze_jewelry_ok"
  },
  {
    "id": "e4fd1e56-bf62-4377-acc0-1cd836310bcf",
    "createdAt": "2026-03-27T19:45:18.646Z",
    "type": "generate",
    "status": "ok",
    "userId": "c0d04b59-e946-4b9f-8d40-2ab44a912ff8",
    "platform": "insta-post",
    "durationMs": 43180,
    "estimatedCostUsd": 0.2,
    "message": "generate_ok"
  },
  {
    "id": "2e711863-0b08-4463-af86-31be155fbbe9",
    "createdAt": "2026-03-27T19:44:35.279Z",
    "type": "analyze_style",
    "status": "ok",
    "userId": "c0d04b59-e946-4b9f-8d40-2ab44a912ff8",
    "durationMs": 7612,
    "estimatedCostUsd": 0.015,
    "message": "analyze_style_ok"
  },
  {
    "id": "18372116-66af-4ade-8a3b-cae8f3effdb7",
    "createdAt": "2026-03-27T19:44:30.712Z",
    "type": "analyze_style",
    "status": "ok",
    "userId": "c0d04b59-e946-4b9f-8d40-2ab44a912ff8",
    "durationMs": 7171,
    "estimatedCostUsd": 0.015,
    "message": "analyze_style_ok"
  },
  {
    "id": "21bafa5f-6405-41b2-80ff-b3c5326db731",
    "createdAt": "2026-03-27T19:43:57.254Z",
    "type": "optimize",
    "status": "ok",
    "userId": "c0d04b59-e946-4b9f-8d40-2ab44a912ff8",
    "durationMs": 5847,
    "estimatedCostUsd": 0.01,
    "message": "optimize_ok"
  },
  {
    "id": "4f72dd31-c36c-4837-b77c-36455afc8648",
    "createdAt": "2026-03-27T18:13:16.794Z",
    "type": "analyze_jewelry",
    "status": "ok",
    "userId": "c0d04b59-e946-4b9f-8d40-2ab44a912ff8",
    "platform": "instagram",
    "durationMs": 11133,
    "estimatedCostUsd": 0.03,
    "message": "analyze_jewelry_ok"
  },
  {
    "id": "f62fafef-ded7-4685-aff6-7742312449ef",
    "createdAt": "2026-03-27T18:12:35.491Z",
    "type": "generate",
    "status": "ok",
    "userId": "c0d04b59-e946-4b9f-8d40-2ab44a912ff8",
    "platform": "insta-post",
    "durationMs": 46972,
    "estimatedCostUsd": 0.2,
    "message": "generate_ok"
  },
  {
    "id": "7027235a-c7c0-4017-8779-818eb30adec6",
    "createdAt": "2026-03-27T18:11:48.476Z",
    "type": "analyze_style",
    "status": "ok",
    "userId": "c0d04b59-e946-4b9f-8d40-2ab44a912ff8",
    "durationMs": 9098,
    "estimatedCostUsd": 0.015,
    "message": "analyze_style_ok"
  },
  {
    "id": "ab248b02-6232-42bb-8f5c-229324a6deae",
    "createdAt": "2026-03-27T18:11:40.667Z",
    "type": "analyze_style",
    "status": "ok",
    "userId": "c0d04b59-e946-4b9f-8d40-2ab44a912ff8",
    "durationMs": 9742,
    "estimatedCostUsd": 0.015,
    "message": "analyze_style_ok"
  },
  {
    "id": "010e650c-3c00-44e9-945b-24f238c46fc4",
    "createdAt": "2026-03-27T18:11:37.257Z",
    "type": "optimize",
    "status": "ok",
    "userId": "c0d04b59-e946-4b9f-8d40-2ab44a912ff8",
    "durationMs": 5274,
    "estimatedCostUsd": 0.01,
    "message": "optimize_ok"
  },
  {
    "id": "0eed55ee-5fc3-4592-b33f-09d1e9e42fda",
    "createdAt": "2026-03-27T18:11:25.157Z",
    "type": "optimize",
    "status": "ok",
    "userId": "c0d04b59-e946-4b9f-8d40-2ab44a912ff8",
    "durationMs": 4831,
    "estimatedCostUsd": 0.01,
    "message": "optimize_ok"
  },
  {
    "id": "6d96fddc-0e0e-4c1d-8951-789c05474c68",
    "createdAt": "2026-03-27T18:03:13.922Z",
    "type": "generate",
    "status": "ok",
    "userId": "c0d04b59-e946-4b9f-8d40-2ab44a912ff8",
    "platform": "insta-post",
    "durationMs": 41765,
    "estimatedCostUsd": 0.2,
    "message": "generate_ok"
  },
  {
    "id": "5a6b0ada-2dc2-4e1f-b5d8-70e2a67b508e",
    "createdAt": "2026-03-27T18:02:27.410Z",
    "type": "optimize",
    "status": "ok",
    "userId": "c0d04b59-e946-4b9f-8d40-2ab44a912ff8",
    "durationMs": 4001,
    "estimatedCostUsd": 0.01,
    "message": "optimize_ok"
  },
  {
    "id": "e46bffbf-f8e1-4b59-a3b4-7880bba538de",
    "createdAt": "2026-03-27T18:02:22.087Z",
    "type": "analyze_style",
    "status": "ok",
    "userId": "c0d04b59-e946-4b9f-8d40-2ab44a912ff8",
    "durationMs": 9042,
    "estimatedCostUsd": 0.015,
    "message": "analyze_style_ok"
  },
  {
    "id": "6e48cf8a-9c3a-402f-816b-c62b56d5a338",
    "createdAt": "2026-03-27T18:01:13.109Z",
    "type": "generate",
    "status": "ok",
    "userId": "c0d04b59-e946-4b9f-8d40-2ab44a912ff8",
    "platform": "insta-post",
    "durationMs": 46128,
    "estimatedCostUsd": 0.2,
    "message": "generate_ok"
  },
  {
    "id": "0ce34125-4192-456a-b105-84098f2470ea",
    "createdAt": "2026-03-27T18:00:26.902Z",
    "type": "analyze_style",
    "status": "ok",
    "userId": "c0d04b59-e946-4b9f-8d40-2ab44a912ff8",
    "durationMs": 12925,
    "estimatedCostUsd": 0.015,
    "message": "analyze_style_ok"
  },
  {
    "id": "6be7b330-f93c-4a85-9198-344f460d01a5",
    "createdAt": "2026-03-27T18:00:14.297Z",
    "type": "optimize",
    "status": "ok",
    "userId": "c0d04b59-e946-4b9f-8d40-2ab44a912ff8",
    "durationMs": 5562,
    "estimatedCostUsd": 0.01,
    "message": "optimize_ok"
  },
  {
    "id": "502c023c-815f-4d79-b2bc-1dbedc458da1",
    "createdAt": "2026-03-27T17:59:06.822Z",
    "type": "optimize",
    "status": "error",
    "userId": "c0d04b59-e946-4b9f-8d40-2ab44a912ff8",
    "durationMs": 620,
    "estimatedCostUsd": 0.01,
    "message": "optimize_error"
  },
  {
    "id": "6d7583fe-ccec-40f9-9d44-7944600713cf",
    "createdAt": "2026-03-27T17:41:58.230Z",
    "type": "analyze_style",
    "status": "ok",
    "userId": "c0d04b59-e946-4b9f-8d40-2ab44a912ff8",
    "durationMs": 9729,
    "estimatedCostUsd": 0.015,
    "message": "analyze_style_ok"
  },
  {
    "id": "dd5cff4a-6119-40ea-89e2-9d192a82d07b",
    "createdAt": "2026-03-27T17:39:28.022Z",
    "type": "analyze_jewelry",
    "status": "error",
    "userId": "c0d04b59-e946-4b9f-8d40-2ab44a912ff8",
    "platform": "instagram",
    "durationMs": 25,
    "estimatedCostUsd": 0,
    "message": "insufficient_credit"
  },
  {
    "id": "a95610f3-e6f4-4d94-a76d-8f212cb78794",
    "createdAt": "2026-03-27T17:37:52.278Z",
    "type": "analyze_jewelry",
    "status": "error",
    "userId": "c0d04b59-e946-4b9f-8d40-2ab44a912ff8",
    "platform": "instagram",
    "durationMs": 39,
    "estimatedCostUsd": 0,
    "message": "insufficient_credit"
  },
  {
    "id": "5adfc8e5-c005-4da8-8296-32c3387342ee",
    "createdAt": "2026-03-27T17:37:24.379Z",
    "type": "generate",
    "status": "ok",
    "userId": "c0d04b59-e946-4b9f-8d40-2ab44a912ff8",
    "platform": "insta-post",
    "durationMs": 43513,
    "estimatedCostUsd": 0.2,
    "message": "generate_ok"
  },
  {
    "id": "90b50c3c-da7e-4f3b-8538-bd4cc986120e",
    "createdAt": "2026-03-27T17:36:36.037Z",
    "type": "optimize",
    "status": "ok",
    "userId": "c0d04b59-e946-4b9f-8d40-2ab44a912ff8",
    "durationMs": 5116,
    "estimatedCostUsd": 0.01,
    "message": "optimize_ok"
  },
  {
    "id": "2328f56b-f5a9-4396-ab5c-f2fe8440e95b",
    "createdAt": "2026-03-27T17:36:35.128Z",
    "type": "analyze_style",
    "status": "ok",
    "userId": "c0d04b59-e946-4b9f-8d40-2ab44a912ff8",
    "durationMs": 8457,
    "estimatedCostUsd": 0.015,
    "message": "analyze_style_ok"
  },
  {
    "id": "2fe540a2-71ed-47a4-a2d9-4f79c21f29e2",
    "createdAt": "2026-03-27T13:57:51.407Z",
    "type": "generate",
    "status": "ok",
    "userId": "c0d04b59-e946-4b9f-8d40-2ab44a912ff8",
    "platform": "insta-post",
    "durationMs": 38622,
    "estimatedCostUsd": 0.2,
    "message": "generate_ok"
  },
  {
    "id": "6fbcde11-ff2e-466c-9aa7-eefe096e64fb",
    "createdAt": "2026-03-27T13:56:55.115Z",
    "type": "optimize",
    "status": "ok",
    "userId": "c0d04b59-e946-4b9f-8d40-2ab44a912ff8",
    "durationMs": 7216,
    "estimatedCostUsd": 0.01,
    "message": "optimize_ok"
  },
  {
    "id": "9da9ce02-0250-46c3-a77d-e59820fd5b85",
    "createdAt": "2026-03-27T13:22:50.075Z",
    "type": "generate",
    "status": "ok",
    "userId": "c0d04b59-e946-4b9f-8d40-2ab44a912ff8",
    "platform": "insta-post",
    "durationMs": 48322,
    "estimatedCostUsd": 0.2,
    "message": "generate_ok"
  },
  {
    "id": "32139877-0c0a-4935-bd68-e298ce8386d7",
    "createdAt": "2026-03-27T13:21:57.952Z",
    "type": "optimize",
    "status": "ok",
    "userId": "c0d04b59-e946-4b9f-8d40-2ab44a912ff8",
    "durationMs": 5073,
    "estimatedCostUsd": 0.01,
    "message": "optimize_ok"
  },
  {
    "id": "2597be4b-70e6-4f27-b923-1524ab0015d0",
    "createdAt": "2026-03-27T13:21:50.594Z",
    "type": "analyze_style",
    "status": "ok",
    "userId": "c0d04b59-e946-4b9f-8d40-2ab44a912ff8",
    "durationMs": 6623,
    "estimatedCostUsd": 0.015,
    "message": "analyze_style_ok"
  },
  {
    "id": "a1eddfbd-3556-4858-a85e-c65f6ffe978a",
    "createdAt": "2026-03-27T13:07:33.837Z",
    "type": "generate",
    "status": "ok",
    "userId": "c0d04b59-e946-4b9f-8d40-2ab44a912ff8",
    "platform": "insta-post",
    "durationMs": 45934,
    "estimatedCostUsd": 0.2,
    "message": "generate_ok"
  },
  {
    "id": "0aae15b6-cf7a-42f4-9355-4b622a643045",
    "createdAt": "2026-03-27T13:06:02.260Z",
    "type": "generate",
    "status": "ok",
    "userId": "c0d04b59-e946-4b9f-8d40-2ab44a912ff8",
    "platform": "insta-post",
    "durationMs": 44286,
    "estimatedCostUsd": 0.2,
    "message": "generate_ok"
  },
  {
    "id": "84724ec2-80be-43ef-8d03-a29c59bc658f",
    "createdAt": "2026-03-27T13:05:17.939Z",
    "type": "analyze_style",
    "status": "ok",
    "userId": "c0d04b59-e946-4b9f-8d40-2ab44a912ff8",
    "durationMs": 6716,
    "estimatedCostUsd": 0.015,
    "message": "analyze_style_ok"
  },
  {
    "id": "35c7b11e-ce3a-4b3e-b993-67ff817ea965",
    "createdAt": "2026-03-27T13:05:13.428Z",
    "type": "analyze_style",
    "status": "ok",
    "userId": "c0d04b59-e946-4b9f-8d40-2ab44a912ff8",
    "durationMs": 6219,
    "estimatedCostUsd": 0.015,
    "message": "analyze_style_ok"
  },
  {
    "id": "c6b40898-b2ec-4bb4-9ae2-00ff384c9595",
    "createdAt": "2026-03-27T13:04:23.554Z",
    "type": "generate",
    "status": "ok",
    "userId": "c0d04b59-e946-4b9f-8d40-2ab44a912ff8",
    "platform": "insta-post",
    "durationMs": 49457,
    "estimatedCostUsd": 0.2,
    "message": "generate_ok"
  },
  {
    "id": "b8d0bedc-764b-4136-a462-fe4a17a32362",
    "createdAt": "2026-03-27T13:03:34.074Z",
    "type": "analyze_style",
    "status": "ok",
    "userId": "c0d04b59-e946-4b9f-8d40-2ab44a912ff8",
    "durationMs": 6308,
    "estimatedCostUsd": 0.015,
    "message": "analyze_style_ok"
  },
  {
    "id": "940f443a-b731-41e7-92e1-4d3c284bc16a",
    "createdAt": "2026-03-27T13:03:31.662Z",
    "type": "analyze_style",
    "status": "ok",
    "userId": "c0d04b59-e946-4b9f-8d40-2ab44a912ff8",
    "durationMs": 7304,
    "estimatedCostUsd": 0.015,
    "message": "analyze_style_ok"
  },
  {
    "id": "580558bc-168d-4796-ad0c-9dac0227c07d",
    "createdAt": "2026-03-27T13:02:47.536Z",
    "type": "generate",
    "status": "ok",
    "userId": "c0d04b59-e946-4b9f-8d40-2ab44a912ff8",
    "platform": "insta-post",
    "durationMs": 42256,
    "estimatedCostUsd": 0.2,
    "message": "generate_ok"
  },
  {
    "id": "78167d24-1f95-4ec5-a95f-7072387e41b8",
    "createdAt": "2026-03-27T13:01:59.436Z",
    "type": "optimize",
    "status": "ok",
    "userId": "c0d04b59-e946-4b9f-8d40-2ab44a912ff8",
    "durationMs": 4143,
    "estimatedCostUsd": 0.01,
    "message": "optimize_ok"
  },
  {
    "id": "2985cce0-c628-419a-a1c8-ee56e4a29849",
    "createdAt": "2026-03-27T12:26:11.488Z",
    "type": "generate",
    "status": "ok",
    "userId": "c0d04b59-e946-4b9f-8d40-2ab44a912ff8",
    "platform": "youtube-web",
    "durationMs": 46947,
    "estimatedCostUsd": 0.2,
    "message": "generate_ok"
  },
  {
    "id": "ed6aef8c-b747-4bb5-ac3f-7cbae21b3a64",
    "createdAt": "2026-03-27T12:25:11.557Z",
    "type": "optimize",
    "status": "ok",
    "userId": "c0d04b59-e946-4b9f-8d40-2ab44a912ff8",
    "durationMs": 6044,
    "estimatedCostUsd": 0.01,
    "message": "optimize_ok"
  },
  {
    "id": "d1885b29-0886-4f31-bce8-357ce9ac87f6",
    "createdAt": "2026-03-27T12:14:18.743Z",
    "type": "generate",
    "status": "ok",
    "userId": "c0d04b59-e946-4b9f-8d40-2ab44a912ff8",
    "platform": "youtube-web",
    "durationMs": 49043,
    "estimatedCostUsd": 0.2,
    "message": "generate_ok"
  },
  {
    "id": "45b70607-3292-45dc-ab51-3a750d081063",
    "createdAt": "2026-03-27T12:12:31.219Z",
    "type": "generate",
    "status": "ok",
    "userId": "c0d04b59-e946-4b9f-8d40-2ab44a912ff8",
    "platform": "youtube-web",
    "durationMs": 51158,
    "estimatedCostUsd": 0.2,
    "message": "generate_ok"
  },
  {
    "id": "b68e8b3e-9896-4d32-a934-a54872d8b811",
    "createdAt": "2026-03-27T12:11:35.819Z",
    "type": "optimize",
    "status": "ok",
    "userId": "c0d04b59-e946-4b9f-8d40-2ab44a912ff8",
    "durationMs": 4083,
    "estimatedCostUsd": 0.01,
    "message": "optimize_ok"
  },
  {
    "id": "a4f03630-26d2-494c-bdca-92acb587ebc9",
    "createdAt": "2026-03-27T11:56:20.722Z",
    "type": "generate",
    "status": "ok",
    "userId": "c0d04b59-e946-4b9f-8d40-2ab44a912ff8",
    "platform": "insta-post",
    "durationMs": 48031,
    "estimatedCostUsd": 0.2,
    "message": "generate_ok"
  },
  {
    "id": "b55df0b4-3339-4e82-ae80-3e87916932d9",
    "createdAt": "2026-03-27T11:55:32.587Z",
    "type": "analyze_style",
    "status": "ok",
    "userId": "c0d04b59-e946-4b9f-8d40-2ab44a912ff8",
    "durationMs": 7999,
    "estimatedCostUsd": 0.015,
    "message": "analyze_style_ok"
  },
  {
    "id": "ac26dd63-e2b6-4146-b4ef-8abf37d3e4eb",
    "createdAt": "2026-03-27T11:54:33.969Z",
    "type": "optimize",
    "status": "ok",
    "userId": "c0d04b59-e946-4b9f-8d40-2ab44a912ff8",
    "durationMs": 4714,
    "estimatedCostUsd": 0.01,
    "message": "optimize_ok"
  },
  {
    "id": "8f911d8b-5a5c-4cdd-b916-dc504bc42912",
    "createdAt": "2026-03-27T11:15:22.532Z",
    "type": "analyze_jewelry",
    "status": "error",
    "userId": "c0d04b59-e946-4b9f-8d40-2ab44a912ff8",
    "platform": "instagram",
    "durationMs": 24,
    "estimatedCostUsd": 0,
    "message": "insufficient_credit"
  },
  {
    "id": "789985e2-d2bb-4557-aed7-f1c745a0e665",
    "createdAt": "2026-03-27T11:14:44.536Z",
    "type": "generate",
    "status": "ok",
    "userId": "c0d04b59-e946-4b9f-8d40-2ab44a912ff8",
    "platform": "insta-post",
    "durationMs": 49399,
    "estimatedCostUsd": 0.2,
    "message": "generate_ok"
  },
  {
    "id": "706fddc0-eab1-43aa-9f9f-f3bf3ef091b6",
    "createdAt": "2026-03-27T11:13:55.001Z",
    "type": "analyze_style",
    "status": "ok",
    "userId": "c0d04b59-e946-4b9f-8d40-2ab44a912ff8",
    "durationMs": 6614,
    "estimatedCostUsd": 0.015,
    "message": "analyze_style_ok"
  },
  {
    "id": "91e726d3-f8e5-4d0c-a59c-a06917a80d18",
    "createdAt": "2026-03-27T11:13:28.873Z",
    "type": "optimize",
    "status": "ok",
    "userId": "c0d04b59-e946-4b9f-8d40-2ab44a912ff8",
    "durationMs": 4049,
    "estimatedCostUsd": 0.01,
    "message": "optimize_ok"
  },
  {
    "id": "b05c09ba-f8fc-422b-af51-359aa031d40f",
    "createdAt": "2026-03-27T11:02:13.714Z",
    "type": "generate",
    "status": "ok",
    "userId": "c0d04b59-e946-4b9f-8d40-2ab44a912ff8",
    "platform": "insta-post",
    "durationMs": 47242,
    "estimatedCostUsd": 0.2,
    "message": "generate_ok"
  },
  {
    "id": "b6678632-77c4-41bc-ae8f-f22f8377bd78",
    "createdAt": "2026-03-27T11:01:26.331Z",
    "type": "analyze_style",
    "status": "ok",
    "userId": "c0d04b59-e946-4b9f-8d40-2ab44a912ff8",
    "durationMs": 5361,
    "estimatedCostUsd": 0.015,
    "message": "analyze_style_ok"
  },
  {
    "id": "a521f002-3217-4f38-888d-44ae4bd466e7",
    "createdAt": "2026-03-27T11:01:08.941Z",
    "type": "optimize",
    "status": "ok",
    "userId": "c0d04b59-e946-4b9f-8d40-2ab44a912ff8",
    "durationMs": 5977,
    "estimatedCostUsd": 0.01,
    "message": "optimize_ok"
  },
  {
    "id": "0308655e-1418-4f54-9963-051c5cf89f28",
    "createdAt": "2026-03-27T10:46:12.600Z",
    "type": "generate",
    "status": "ok",
    "userId": "c0d04b59-e946-4b9f-8d40-2ab44a912ff8",
    "platform": "insta-post",
    "durationMs": 46675,
    "estimatedCostUsd": 0.2,
    "message": "generate_ok"
  },
  {
    "id": "928b4866-83f9-40fc-9bac-e41f27e79eb0",
    "createdAt": "2026-03-27T10:36:17.536Z",
    "type": "generate",
    "status": "ok",
    "userId": "c0d04b59-e946-4b9f-8d40-2ab44a912ff8",
    "platform": "insta-post",
    "durationMs": 44433,
    "estimatedCostUsd": 0.2,
    "message": "generate_ok"
  },
  {
    "id": "8cf5cf94-2e7d-419d-bb89-fd55c10cff1a",
    "createdAt": "2026-03-27T10:34:23.868Z",
    "type": "generate",
    "status": "ok",
    "userId": "c0d04b59-e946-4b9f-8d40-2ab44a912ff8",
    "platform": "insta-post",
    "durationMs": 51088,
    "estimatedCostUsd": 0.2,
    "message": "generate_ok"
  },
  {
    "id": "4aa19e6f-9a96-44eb-8a09-1767538be675",
    "createdAt": "2026-03-27T10:33:32.699Z",
    "type": "analyze_style",
    "status": "ok",
    "userId": "c0d04b59-e946-4b9f-8d40-2ab44a912ff8",
    "durationMs": 6082,
    "estimatedCostUsd": 0.015,
    "message": "analyze_style_ok"
  },
  {
    "id": "b7f498a1-d55f-41cc-873d-3e14eed7118b",
    "createdAt": "2026-03-27T10:33:22.044Z",
    "type": "optimize",
    "status": "ok",
    "userId": "c0d04b59-e946-4b9f-8d40-2ab44a912ff8",
    "durationMs": 5247,
    "estimatedCostUsd": 0.01,
    "message": "optimize_ok"
  },
  {
    "id": "ceccd00e-51e2-4308-b7c6-f9fbc3012f22",
    "createdAt": "2026-03-26T10:22:25.499Z",
    "type": "analyze_jewelry",
    "status": "error",
    "userId": "c0d04b59-e946-4b9f-8d40-2ab44a912ff8",
    "platform": "instagram",
    "durationMs": 37,
    "estimatedCostUsd": 0,
    "message": "insufficient_credit"
  },
  {
    "id": "1abb8902-3af4-442d-8872-ed6984bf3566",
    "createdAt": "2026-03-26T10:21:31.398Z",
    "type": "generate",
    "status": "ok",
    "userId": "c0d04b59-e946-4b9f-8d40-2ab44a912ff8",
    "platform": "insta-post",
    "durationMs": 50118,
    "estimatedCostUsd": 0.2,
    "message": "generate_ok"
  },
  {
    "id": "b2e90a61-0e6b-408f-a5dd-c20366e08ef1",
    "createdAt": "2026-03-26T10:20:41.250Z",
    "type": "analyze_style",
    "status": "ok",
    "userId": "c0d04b59-e946-4b9f-8d40-2ab44a912ff8",
    "durationMs": 7225,
    "estimatedCostUsd": 0.015,
    "message": "analyze_style_ok"
  },
  {
    "id": "01dddf63-439b-46fe-bc69-1b762ad024ad",
    "createdAt": "2026-03-26T10:20:02.859Z",
    "type": "generate",
    "status": "ok",
    "userId": "c0d04b59-e946-4b9f-8d40-2ab44a912ff8",
    "platform": "insta-post",
    "durationMs": 32562,
    "estimatedCostUsd": 0.2,
    "message": "generate_ok"
  },
  {
    "id": "2eaed617-1c8c-4603-9c0a-ea5f2da3cb63",
    "createdAt": "2026-03-26T10:19:26.571Z",
    "type": "optimize",
    "status": "ok",
    "userId": "c0d04b59-e946-4b9f-8d40-2ab44a912ff8",
    "durationMs": 6106,
    "estimatedCostUsd": 0.01,
    "message": "optimize_ok"
  },
  {
    "id": "fc3526e0-4d9a-4497-b450-a55e9ff5cb4d",
    "createdAt": "2026-03-26T10:18:28.380Z",
    "type": "generate",
    "status": "ok",
    "userId": "c0d04b59-e946-4b9f-8d40-2ab44a912ff8",
    "platform": "insta-post",
    "durationMs": 35421,
    "estimatedCostUsd": 0.2,
    "message": "generate_ok"
  },
  {
    "id": "9a7d1cce-1fd2-4c20-b709-e850f3d04bd1",
    "createdAt": "2026-03-26T10:17:32.188Z",
    "type": "generate",
    "status": "ok",
    "userId": "c0d04b59-e946-4b9f-8d40-2ab44a912ff8",
    "platform": "insta-post",
    "durationMs": 35158,
    "estimatedCostUsd": 0.2,
    "message": "generate_ok"
  },
  {
    "id": "78b98f05-68b1-42a3-9d80-c3493dc042fe",
    "createdAt": "2026-03-26T10:16:48.946Z",
    "type": "optimize",
    "status": "ok",
    "userId": "c0d04b59-e946-4b9f-8d40-2ab44a912ff8",
    "durationMs": 4811,
    "estimatedCostUsd": 0.01,
    "message": "optimize_ok"
  },
  {
    "id": "565198a2-6be9-4ba5-ac25-1e02c993b923",
    "createdAt": "2026-03-22T21:59:50.780Z",
    "type": "generate",
    "status": "ok",
    "userId": "c0d04b59-e946-4b9f-8d40-2ab44a912ff8",
    "platform": "insta-post",
    "durationMs": 42492,
    "estimatedCostUsd": 0.2,
    "message": "generate_ok"
  },
  {
    "id": "249031d0-aca1-46c7-9290-ae1d44db5221",
    "createdAt": "2026-03-22T21:57:18.074Z",
    "type": "generate",
    "status": "ok",
    "userId": "c0d04b59-e946-4b9f-8d40-2ab44a912ff8",
    "platform": "insta-post",
    "durationMs": 44294,
    "estimatedCostUsd": 0.2,
    "message": "generate_ok"
  },
  {
    "id": "02954d43-54b6-4eda-943b-70e64ecace4a",
    "createdAt": "2026-03-22T21:56:07.324Z",
    "type": "optimize",
    "status": "ok",
    "userId": "c0d04b59-e946-4b9f-8d40-2ab44a912ff8",
    "durationMs": 4135,
    "estimatedCostUsd": 0.01,
    "message": "optimize_ok"
  },
  {
    "id": "a369b732-1db1-400d-867e-72bc61df2b2a",
    "createdAt": "2026-03-22T21:43:48.459Z",
    "type": "analyze_jewelry",
    "status": "error",
    "userId": "c0d04b59-e946-4b9f-8d40-2ab44a912ff8",
    "platform": "instagram",
    "durationMs": 25,
    "estimatedCostUsd": 0,
    "message": "insufficient_credit"
  },
  {
    "id": "58cacde3-f002-4ed3-b5f1-4415d6f9420c",
    "createdAt": "2026-03-22T21:39:58.499Z",
    "type": "generate",
    "status": "ok",
    "userId": "c0d04b59-e946-4b9f-8d40-2ab44a912ff8",
    "platform": "insta-post",
    "durationMs": 44105,
    "estimatedCostUsd": 0.2,
    "message": "generate_ok"
  },
  {
    "id": "c37882f4-5f7e-476e-ab27-e7418474adab",
    "createdAt": "2026-03-22T21:39:14.180Z",
    "type": "analyze_style",
    "status": "ok",
    "userId": "c0d04b59-e946-4b9f-8d40-2ab44a912ff8",
    "durationMs": 8170,
    "estimatedCostUsd": 0.015,
    "message": "analyze_style_ok"
  },
  {
    "id": "276d00fe-4026-4628-9c69-32d23fd29728",
    "createdAt": "2026-03-22T21:38:46.830Z",
    "type": "optimize",
    "status": "ok",
    "userId": "c0d04b59-e946-4b9f-8d40-2ab44a912ff8",
    "durationMs": 4394,
    "estimatedCostUsd": 0.01,
    "message": "optimize_ok"
  }
]